localstack_typedb/__init__.py
localstack_typedb/extension.py
localstack_typedb/utils/__init__.py
localstack_typedb/utils/docker.py
localstack_typedb/utils/h2_proxy.py
localstack_extension_typedb-0.1.1.dist-info/METADATA
localstack_extension_typedb-0.1.1.dist-info/WHEEL
localstack_extension_typedb-0.1.1.dist-info/entry_points.txt
localstack_extension_typedb-0.1.1.dist-info/top_level.txt
localstack_extension_typedb-0.1.1.dist-info/RECORD
