Metadata-Version: 2.4
Name: localstack-extension-typedb
Version: 0.1.1
Summary: LocalStack Extension: TypeDB on LocalStack
Author: LocalStack + TypeDB team
Project-URL: Homepage, https://github.com/localstack/localstack-extensions
Keywords: LocalStack,TypeDB
Requires-Python: >=3.9
Requires-Dist: httpx
Requires-Dist: h2
Requires-Dist: priority
Provides-Extra: dev
Requires-Dist: boto3; extra == "dev"
Requires-Dist: build; extra == "dev"
Requires-Dist: jsonpatch; extra == "dev"
Requires-Dist: localstack; extra == "dev"
Requires-Dist: pytest; extra == "dev"
Requires-Dist: rolo; extra == "dev"
Requires-Dist: ruff; extra == "dev"
Requires-Dist: twisted; extra == "dev"
Requires-Dist: typedb-driver; extra == "dev"
